jsonStreet/__init__.py
jsonStreet/street.py
jsonstreet-0.0.3.dist-info/METADATA
jsonstreet-0.0.3.dist-info/WHEEL
jsonstreet-0.0.3.dist-info/licenses/LICENSE
jsonstreet-0.0.3.dist-info/RECORD
