Metadata-Version: 2.1
Name: jsonStreet
Version: 0.0.3
Summary: Traverse JSON ... Safely
Project-URL: Homepage, https://pypi.org/project/jsonStreet
Project-URL: Bug Tracker, https://github.com/pypa/sampleproject/issues
Author-email: Maxim Maeder <info@maximmaeder.com>
License: Copyright (c) 2018 The Python Packaging Authority
Classifier: License :: OSI Approved :: MIT License
Classifier: Operating System :: OS Independent
Classifier: Programming Language :: Python :: 3
Requires-Python: >=3.7
